./.gitignore
./PKG-INFO
./README.md
./pyproject.toml
./vision_agents/plugins/kokoro/__init__.py
./vision_agents/plugins/kokoro/tts.py
vision_agents_plugins_kokoro-0.2.10.dist-info/METADATA
vision_agents_plugins_kokoro-0.2.10.dist-info/WHEEL
vision_agents_plugins_kokoro-0.2.10.dist-info/RECORD
