Metadata-Version: 2.4
Name: vision-agents-plugins-kokoro
Version: 0.2.10
Summary: Kokoro TTS integration for Vision Agents
Project-URL: Documentation, https://visionagents.ai/
Project-URL: Website, https://visionagents.ai/
Project-URL: Source, https://github.com/GetStream/Vision-Agents
License-Expression: MIT
Keywords: AI,TTS,agents,kokoro,text-to-speech,voice agents
Requires-Python: >=3.10
Requires-Dist: kokoro>=0.9.4
Requires-Dist: misaki[en]>=0.9.4
Requires-Dist: numpy<2.3,>=2.2.6
Requires-Dist: vision-agents
